[
  {
    "changes": "profile.breakout_long_no_0dte.es-structure.min-score=5; profile.breakout_long_no_0dte.es-vwap.slope-min=0.1; profile.breakout_long_no_0dte.take-profit.distance=4; profile.pullback_long_no_0dte.es-structure.min-score=5",
    "delta_average_mae": 1.5634978229317937,
    "delta_net_profit": -241.40000000000055,
    "delta_score": -240.0367588211575,
    "delta_slow_12h_trades": 0.0,
    "delta_trades": -2.0,
    "delta_worst_mae": 0.0,
    "family": "take-profit",
    "from_run": "run_001",
    "label": "fallback-es-quality-box",
    "primary_metric": "net_profit",
    "reason": "score delta -240.037 < 0; net profit delta -241.4 < -25",
    "result": "mixed",
    "to_run": "run_002"
  },
  {
    "changes": "entry-veto-charm-pin-tail-risk-max-adx=20; entry-veto-charm-pin-tail-risk-max-rolling-high-distance=15; entry-veto-charm-pin-tail-risk-min-setup-quality-score=60; use-entry-veto-charm-pin-tail-risk-signature=true",
    "delta_average_mae": -1.5634978229317937,
    "delta_net_profit": 241.40000000000055,
    "delta_score": 240.0367588211575,
    "delta_slow_12h_trades": 0.0,
    "delta_trades": 2.0,
    "delta_worst_mae": 0.0,
    "family": "runtime-risk",
    "from_run": "run_002",
    "label": "charm-pin-tail-risk-capture",
    "primary_metric": "worst_mae",
    "reason": "score delta 240.037 >= 0; net profit delta 241.4 >= -25; trade drop 0% <= 10%; MAE delta 0 >= 0; slow trades delta 0 <= 0",
    "result": "accepted",
    "to_run": "run_005"
  },
  {
    "changes": "profile.breakout_long_no_0dte.enabled=false; profile.pullback_long_no_0dte.es-vwap.max-distance=8; profile.pullback_long_no_0dte.take-profit.distance=3; profile.squeeze_long_no_0dte.enabled=false",
    "delta_average_mae": 1.315384615384616,
    "delta_net_profit": -23.399999999999636,
    "delta_score": -21.432798076923063,
    "delta_slow_12h_trades": 0.0,
    "delta_trades": 0.0,
    "delta_worst_mae": 0.0,
    "family": "take-profit",
    "from_run": "run_003",
    "label": "fallback-prune-pullback-retain",
    "primary_metric": "net_profit",
    "reason": "score delta -21.4328 < 0",
    "result": "mixed",
    "to_run": "run_006"
  },
  {
    "changes": "profile.breakout_long_1dte.es-structure.min-score=4; profile.breakout_long_1dte.es-vwap.slope-min=0.04; profile.breakout_long_1dte.long-regime-filter-1dte.min-forward-dex-ratio-30m=0.08; profile.breakout_long_1dte.take-profit.max-distance=6",
    "delta_average_mae": -6.491832611832621,
    "delta_net_profit": -317.09999999999945,
    "delta_score": -355.72553225108277,
    "delta_slow_12h_trades": 0.0,
    "delta_trades": -6.0,
    "delta_worst_mae": -76.75,
    "family": "take-profit",
    "from_run": "run_004",
    "label": "batch-g-1dte-quality-tighten",
    "primary_metric": "net_profit",
    "reason": "score delta -355.726 < 0; net profit delta -317.1 < -25",
    "result": "mixed",
    "to_run": "run_007"
  },
  {
    "changes": "profile.breakout_long_1dte.es-structure.min-score=4; profile.breakout_long_1dte.es-vwap.slope-min=0.04; profile.breakout_long_1dte.take-profit.max-distance=6",
    "delta_average_mae": -4.300624166190204,
    "delta_net_profit": -558.5,
    "delta_score": -594.3322056937286,
    "delta_slow_12h_trades": 0.0,
    "delta_trades": -7.0,
    "delta_worst_mae": -76.75,
    "family": "take-profit",
    "from_run": "run_005",
    "label": "1dte-local-quality-gate",
    "primary_metric": "net_profit",
    "reason": "score delta -594.332 < 0; net profit delta -558.5 < -25",
    "result": "mixed",
    "to_run": "run_008"
  },
  {
    "changes": "option-call-volume.min-increase-pct=0.05; profile.call_wall_acceptance_long.dynamic-take-profit.max=7; profile.call_wall_acceptance_long.long-regime-filter.min-forward-dex-ratio-30m=0.03; profile.call_wall_acceptance_long.long-regime-filter.min-net-dex-volume=7.5e+08",
    "delta_average_mae": -7.357831086439333,
    "delta_net_profit": -481.60000000000036,
    "delta_score": -529.7279188518805,
    "delta_slow_12h_trades": 0.0,
    "delta_trades": -7.0,
    "delta_worst_mae": -111.75,
    "family": "take-profit",
    "from_run": "run_006",
    "label": "promote",
    "primary_metric": "net_profit",
    "reason": "score delta -529.728 < 0; net profit delta -481.6 < -25",
    "result": "mixed",
    "to_run": "run_009"
  },
  {
    "changes": "option-call-volume.min-increase-pct=0.05; option-strike-acceptance-seconds=30; profile.call_wall_acceptance_long.long-regime-filter.min-forward-dex-ratio-30m=0.03; profile.call_wall_acceptance_long.long-regime-filter.min-net-dex-volume=7.5e+08",
    "delta_average_mae": 0.5591540404040387,
    "delta_net_profit": -305.8000000000002,
    "delta_score": -314.1561856060598,
    "delta_slow_12h_trades": 0.0,
    "delta_trades": -3.0,
    "delta_worst_mae": -35.0,
    "family": "option-strike-map",
    "from_run": "run_007",
    "label": "call-wall-sample-expansion",
    "primary_metric": "score",
    "reason": "score delta -314.156 < 0; net profit delta -305.8 < -25",
    "result": "mixed",
    "to_run": "run_010"
  },
  {
    "changes": "option-call-volume.min-increase-pct=0.05; option-strike-acceptance-seconds=30; profile.call_wall_acceptance_long.long-regime-filter.min-net-dex-volume=7.5e+08",
    "delta_average_mae": 0.5591540404040387,
    "delta_net_profit": -305.8000000000002,
    "delta_score": -314.1561856060598,
    "delta_slow_12h_trades": 0.0,
    "delta_trades": -3.0,
    "delta_worst_mae": -35.0,
    "family": "option-strike-map",
    "from_run": "run_008",
    "label": "promote",
    "primary_metric": "score",
    "reason": "score delta -314.156 < 0; net profit delta -305.8 < -25",
    "result": "mixed",
    "to_run": "run_011"
  },
  {
    "changes": "trade-risk-max-adverse-points=12; use-stale-trade-exit=true; use-trade-health-exit=true",
    "delta_average_mae": 10.168265559373808,
    "delta_net_profit": -544.1999999999998,
    "delta_score": -4668.628704438717,
    "delta_slow_12h_trades": 0.0,
    "delta_trades": 12.0,
    "delta_worst_mae": 246.75,
    "family": "runtime-risk",
    "from_run": "run_009",
    "label": "runtime-risk-validation",
    "primary_metric": "worst_mae",
    "reason": "score delta -4668.63 < 0; net profit delta -544.2 < -25",
    "result": "mixed",
    "to_run": "run_012"
  },
  {
    "changes": "__router.one-dte-profiles=breakout_long_1dte,pullback_long_1dte",
    "delta_average_mae": 4.570773809523814,
    "delta_net_profit": 747.6999999999998,
    "delta_score": 792.6110218253962,
    "delta_slow_12h_trades": 0.0,
    "delta_trades": 9.0,
    "delta_worst_mae": 111.75,
    "family": "general",
    "from_run": "run_010",
    "label": "1dte-pullback-companion-activation",
    "primary_metric": "score",
    "reason": "score delta 792.611 >= 0; net profit delta 747.7 >= -25; trade drop 0% <= 10%",
    "result": "accepted",
    "to_run": "run_013"
  },
  {
    "changes": "entry-veto-charm-pin-tail-risk-max-pullback-from-high=10; entry-veto-charm-pin-tail-risk-max-rolling-high-distance=15; entry-veto-charm-pin-tail-risk-min-setup-quality-score=60",
    "delta_average_mae": 3.741470125786165,
    "delta_net_profit": 864.3000000000002,
    "delta_score": 908.4883912997884,
    "delta_slow_12h_trades": 0.0,
    "delta_trades": 10.0,
    "delta_worst_mae": 111.75,
    "family": "runtime-risk",
    "from_run": "run_011",
    "label": "charm-pin-tail-box-nudge",
    "primary_metric": "worst_mae",
    "reason": "score delta 908.488 >= 0; net profit delta 864.3 >= -25; trade drop 0% <= 10%; MAE delta 111.75 >= 0; slow trades delta 0 <= 0",
    "result": "accepted",
    "to_run": "run_014"
  },
  {
    "changes": "profile.pullback_long.es-structure.min-score=4; profile.pullback_long.es-vwap.max-distance=8.5",
    "delta_average_mae": -0.5814668615984431,
    "delta_net_profit": 313.40000000000055,
    "delta_score": 4484.84337748538,
    "delta_slow_12h_trades": 0.0,
    "delta_trades": -14.0,
    "delta_worst_mae": -135.0,
    "family": "strategy-profile",
    "from_run": "run_012",
    "label": "promote",
    "primary_metric": "score",
    "reason": "trade drop 12.7273% > 10%",
    "result": "mixed",
    "to_run": "run_015"
  },
  {
    "changes": "profile.charm_wall_breakaway_long.es-structure.min-higher-high-distance=1.5; profile.charm_wall_breakaway_long.es-structure.min-higher-low-distance=1; profile.charm_wall_breakaway_long.long-regime-filter.max-distance-above-charm-wall=15",
    "delta_average_mae": 0.7989497107254095,
    "delta_net_profit": -178.89999999999964,
    "delta_score": -176.68046432280062,
    "delta_slow_12h_trades": 0.0,
    "delta_trades": 2.0,
    "delta_worst_mae": 0.0,
    "family": "strategy-profile",
    "from_run": "run_013",
    "label": "charm-wall-breakaway-structure-gate",
    "primary_metric": "score",
    "reason": "score delta -176.68 < 0; net profit delta -178.9 < -25",
    "result": "mixed",
    "to_run": "run_016"
  },
  {
    "changes": "entry-veto-charm-pin-tail-risk-max-rolling-high-distance=14.75; entry-veto-charm-pin-tail-risk-min-setup-quality-score=60; entry-veto-charm-pin-tail-risk-min-vwap-distance=20",
    "delta_average_mae": 0.0,
    "delta_net_profit": 0.0,
    "delta_score": 0.0,
    "delta_slow_12h_trades": 0.0,
    "delta_trades": 0.0,
    "delta_worst_mae": 0.0,
    "family": "runtime-risk",
    "from_run": "run_014",
    "label": "charm-pin-high-extension-tail-box",
    "primary_metric": "worst_mae",
    "reason": "score delta 0 >= 0; net profit delta 0 >= -25; trade drop 0% <= 10%; MAE delta 0 >= 0; slow trades delta 0 <= 0",
    "result": "accepted",
    "to_run": "run_017"
  },
  {
    "changes": "profile.pullback_long.dynamic-take-profit.max=5; profile.pullback_long.es-vwap.max-distance=12; profile.pullback_long.take-profit.distance=2.5",
    "delta_average_mae": -24.43315789473685,
    "delta_net_profit": 44.399999999999636,
    "delta_score": -1730.9681156965207,
    "delta_slow_12h_trades": 1.0,
    "delta_trades": 0.0,
    "delta_worst_mae": -1499.5,
    "family": "take-profit",
    "from_run": "run_015",
    "label": "promote",
    "primary_metric": "net_profit",
    "reason": "score delta -1730.97 < 0",
    "result": "mixed",
    "to_run": "run_018"
  },
  {
    "changes": "profile.squeeze_long.dynamic-take-profit.max=7.5; profile.squeeze_long.es-vwap.slope-min=0.05; profile.squeeze_long.take-profit.distance=4.25",
    "delta_average_mae": -3.6618709561466574,
    "delta_net_profit": 157.30000000000018,
    "delta_score": 116.71464078800273,
    "delta_slow_12h_trades": 0.0,
    "delta_trades": -3.0,
    "delta_worst_mae": -111.75,
    "family": "take-profit",
    "from_run": "run_016",
    "label": "squeeze-upside-capture",
    "primary_metric": "net_profit",
    "reason": "score delta 116.715 >= 0; net profit delta 157.3 >= -25; trade drop 2.77778% <= 10%",
    "result": "accepted",
    "to_run": "run_019"
  },
  {
    "changes": "profile.squeeze_long.dynamic-take-profit.max=7.5; profile.squeeze_long.take-profit.distance=4.25",
    "delta_average_mae": 0.0,
    "delta_net_profit": 0.0,
    "delta_score": 0.0,
    "delta_slow_12h_trades": 0.0,
    "delta_trades": 0.0,
    "delta_worst_mae": 0.0,
    "family": "take-profit",
    "from_run": "run_017",
    "label": "squeeze-upside-capture-check",
    "primary_metric": "net_profit",
    "reason": "score delta 0 >= 0; net profit delta 0 >= -25; trade drop 0% <= 10%",
    "result": "accepted",
    "to_run": "run_020"
  },
  {
    "changes": "profile.squeeze_long.dynamic-take-profit.max=8; profile.squeeze_long.es-vwap.slope-min=0.06; profile.squeeze_long.take-profit.distance=4.5",
    "delta_average_mae": 19.19032581453635,
    "delta_net_profit": 848.6000000000004,
    "delta_score": 2587.456734242888,
    "delta_slow_12h_trades": -1.0,
    "delta_trades": 10.0,
    "delta_worst_mae": 1387.75,
    "family": "take-profit",
    "from_run": "run_018",
    "label": "promote",
    "primary_metric": "net_profit",
    "reason": "score delta 2587.46 >= 0; net profit delta 848.6 >= -25; trade drop 0% <= 10%",
    "result": "accepted",
    "to_run": "run_021"
  },
  {
    "changes": "profile.squeeze_long.dynamic-take-profit.max=8; profile.squeeze_long.es-vwap.slope-min=0.05; profile.squeeze_long.take-profit.distance=4.25",
    "delta_average_mae": 0.0,
    "delta_net_profit": 0.0,
    "delta_score": 0.0,
    "delta_slow_12h_trades": 0.0,
    "delta_trades": 0.0,
    "delta_worst_mae": 0.0,
    "family": "take-profit",
    "from_run": "run_019",
    "label": "squeeze-dynamic-cap-probe",
    "primary_metric": "net_profit",
    "reason": "score delta 0 >= 0; net profit delta 0 >= -25; trade drop 0% <= 10%",
    "result": "accepted",
    "to_run": "run_022"
  },
  {
    "changes": "profile.charm_wall_breakaway_long.es-vwap.max-distance=22; profile.charm_wall_breakaway_long.take-profit.max-distance=10; profile.charm_wall_breakaway_long.take-profit.multiplier=1.15",
    "delta_average_mae": 0.6981132075471805,
    "delta_net_profit": -146.69999999999982,
    "delta_score": -143.6358412997888,
    "delta_slow_12h_trades": 0.0,
    "delta_trades": 4.0,
    "delta_worst_mae": 0.0,
    "family": "take-profit",
    "from_run": "run_020",
    "label": "charm-wall-exit-compression",
    "primary_metric": "net_profit",
    "reason": "score delta -143.636 < 0; net profit delta -146.7 < -25",
    "result": "mixed",
    "to_run": "run_023"
  },
  {
    "changes": "profile.breakout_long_no_0dte.es-structure.min-score=5; profile.breakout_long_no_0dte.es-vwap.slope-min=0.1; profile.breakout_long_no_0dte.take-profit.distance=4",
    "delta_average_mae": 2.326190476190476,
    "delta_net_profit": -157.20000000000073,
    "delta_score": -120.11248928571513,
    "delta_slow_12h_trades": 0.0,
    "delta_trades": 0.0,
    "delta_worst_mae": 111.75,
    "family": "take-profit",
    "from_run": "run_021",
    "label": "no-0dte-breakout-quality-holdout",
    "primary_metric": "net_profit",
    "reason": "score delta -120.112 < 0; net profit delta -157.2 < -25",
    "result": "mixed",
    "to_run": "run_024"
  },
  {
    "changes": "__router.valid-0dte-profiles=breakout_long,pullback_long,squeeze_long,wall_reclaim_long,wall_breakout_retest_long,late_day_pin_fade,negative_gamma_momentum_long,trend_day_pullback_long,charm_pin_pullback_long,charm_wall_breakaway_long,call_wall_acceptance_long,charm_wall_pin_avoid_long; profile.charm_wall_pin_avoid_long.enabled=true",
    "delta_average_mae": 2.0336175616835988,
    "delta_net_profit": 138.19999999999982,
    "delta_score": 175.84319300919014,
    "delta_slow_12h_trades": 0.0,
    "delta_trades": 2.0,
    "delta_worst_mae": 111.75,
    "family": "strategy-profile",
    "from_run": "run_022",
    "label": "charm-wall-pin-avoid-activation-probe",
    "primary_metric": "score",
    "reason": "score delta 175.843 >= 0; net profit delta 138.2 >= -25; trade drop 0% <= 10%",
    "result": "accepted",
    "to_run": "run_025"
  },
  {
    "changes": "profile.charm_pin_pullback_long.long-regime-filter.dynamic-vwap-expected-move-fraction=0.2; profile.charm_pin_pullback_long.long-regime-filter.dynamic-vwap-max-distance=25; profile.charm_pin_pullback_long.long-regime-filter.recent-high-rejection-min-pullback=8",
    "delta_average_mae": -2.028365384615384,
    "delta_net_profit": 13.0,
    "delta_score": 6.940582478633587,
    "delta_slow_12h_trades": 0.0,
    "delta_trades": -6.0,
    "delta_worst_mae": 0.0,
    "family": "strategy-profile",
    "from_run": "run_023",
    "label": "charm-pin-dynamic-vwap-tail-trim",
    "primary_metric": "score",
    "reason": "score delta 6.94058 >= 0; net profit delta 13 >= -25; trade drop 5.40541% <= 10%",
    "result": "accepted",
    "to_run": "run_026"
  },
  {
    "changes": "profile.charm_wall_breakaway_long.es-structure.min-higher-high-distance=0.5; profile.charm_wall_breakaway_long.long-regime-filter.max-distance-above-charm-wall=25",
    "delta_average_mae": -2.5038095238095224,
    "delta_net_profit": 221.0,
    "delta_score": 217.24158015872854,
    "delta_slow_12h_trades": 0.0,
    "delta_trades": 0.0,
    "delta_worst_mae": 0.0,
    "family": "strategy-profile",
    "from_run": "run_024",
    "label": "charm-wall-admission-probe",
    "primary_metric": "score",
    "reason": "score delta 217.242 >= 0; net profit delta 221 >= -25; trade drop 0% <= 10%",
    "result": "accepted",
    "to_run": "run_027"
  },
  {
    "changes": "profile.charm_pin_pullback_long.long-regime-filter.dynamic-vwap-volatility-multiplier=0.25; profile.charm_pin_pullback_long.long-regime-filter.recent-high-rejection-min-pullback=8",
    "delta_average_mae": 0.0,
    "delta_net_profit": 0.0,
    "delta_score": 0.0,
    "delta_slow_12h_trades": 0.0,
    "delta_trades": 0.0,
    "delta_worst_mae": 0.0,
    "family": "strategy-profile",
    "from_run": "run_025",
    "label": "charm-pin-dynamic-rejection-box",
    "primary_metric": "score",
    "reason": "score delta 0 >= 0; net profit delta 0 >= -25; trade drop 0% <= 10%",
    "result": "accepted",
    "to_run": "run_028"
  },
  {
    "changes": "entry-veto-extended-vwap-rejection-max-vwap-distance=26.25",
    "delta_average_mae": 2.533082365747461,
    "delta_net_profit": 157.5,
    "delta_score": 165.29669854862004,
    "delta_slow_12h_trades": 0.0,
    "delta_trades": 2.0,
    "delta_worst_mae": 13.600000000000023,
    "family": "surgical-veto",
    "from_run": "run_026",
    "label": "surgical-extended-vwap-boundary-probe",
    "primary_metric": "worst_mae",
    "reason": "score delta 165.297 >= 0; net profit delta 157.5 >= -25; trade drop 0% <= 10%; MAE delta 13.6 >= 0; slow trades delta 0 <= 0",
    "result": "accepted",
    "to_run": "run_029"
  },
  {
    "changes": "profile.charm_wall_breakaway_long.long-regime-filter.max-distance-above-charm-wall=25",
    "delta_average_mae": 0.0,
    "delta_net_profit": 0.0,
    "delta_score": 0.0,
    "delta_slow_12h_trades": 0.0,
    "delta_trades": 0.0,
    "delta_worst_mae": 0.0,
    "family": "strategy-profile",
    "from_run": "run_027",
    "label": "charm-wall-geometry-followthrough",
    "primary_metric": "score",
    "reason": "score delta 0 >= 0; net profit delta 0 >= -25; trade drop 0% <= 10%",
    "result": "accepted",
    "to_run": "run_030"
  },
  {
    "changes": "order-book-min-microprice-slope-points-per-second=-0.003",
    "delta_average_mae": 0.0,
    "delta_net_profit": 0.0,
    "delta_score": 0.0,
    "delta_slow_12h_trades": 0.0,
    "delta_trades": 0.0,
    "delta_worst_mae": 0.0,
    "family": "upstream-entry",
    "from_run": "run_028",
    "label": "fallback-orderbookminmicropriceslopepointspersecond--0.003",
    "primary_metric": "score",
    "reason": "score delta 0 >= 0; net profit delta 0 >= -25; trade drop 0% <= 10%",
    "result": "accepted",
    "to_run": "run_031"
  },
  {
    "changes": "entry-veto-extended-vwap-rejection-max-rsi-slope=4.1",
    "delta_average_mae": 2.090475326560224,
    "delta_net_profit": -80.10000000000036,
    "delta_score": -77.93580367682625,
    "delta_slow_12h_trades": 0.0,
    "delta_trades": -2.0,
    "delta_worst_mae": 0.0,
    "family": "surgical-veto",
    "from_run": "run_029",
    "label": "extended-vwap-rsi-boundary-probe",
    "primary_metric": "worst_mae",
    "reason": "score delta -77.9358 < 0; net profit delta -80.1 < -25",
    "result": "mixed",
    "to_run": "run_032"
  },
  {
    "changes": "profile.squeeze_long.dynamic-take-profit.max=5.5; profile.squeeze_long.es-vwap.slope-min=0.05; profile.squeeze_long.take-profit.distance=3.25",
    "delta_average_mae": -0.526304945054946,
    "delta_net_profit": -93.0,
    "delta_score": -127.8808379731363,
    "delta_slow_12h_trades": 0.0,
    "delta_trades": -1.0,
    "delta_worst_mae": -111.75,
    "family": "take-profit",
    "from_run": "run_030",
    "label": "squeeze-fast-realization",
    "primary_metric": "net_profit",
    "reason": "score delta -127.881 < 0; net profit delta -93 < -25",
    "result": "mixed",
    "to_run": "run_033"
  },
  {
    "changes": "profile.breakout_long_no_0dte.es-structure.min-score=5; profile.breakout_long_no_0dte.es-vwap.slope-min=0.1; profile.breakout_long_no_0dte.take-profit.distance=2.5",
    "delta_average_mae": 3.405494159928125,
    "delta_net_profit": -217.60000000000036,
    "delta_score": -209.98805042677304,
    "delta_slow_12h_trades": 0.0,
    "delta_trades": -1.0,
    "delta_worst_mae": 13.600000000000023,
    "family": "take-profit",
    "from_run": "run_031",
    "label": "promote",
    "primary_metric": "net_profit",
    "reason": "score delta -209.988 < 0; net profit delta -217.6 < -25",
    "result": "mixed",
    "to_run": "run_034"
  },
  {
    "changes": "profile.breakout_long_no_0dte.dynamic-take-profit.max=4; profile.breakout_long_no_0dte.es-vwap.slope-min=0.1; profile.breakout_long_no_0dte.take-profit.distance=2.5",
    "delta_average_mae": -0.21924891146589687,
    "delta_net_profit": -12.5,
    "delta_score": -11.853442811643617,
    "delta_slow_12h_trades": 0.0,
    "delta_trades": 2.0,
    "delta_worst_mae": 0.0,
    "family": "take-profit",
    "from_run": "run_032",
    "label": "stale-no-0dte-breakout-compression",
    "primary_metric": "net_profit",
    "reason": "score delta -11.8534 < 0",
    "result": "mixed",
    "to_run": "run_035"
  },
  {
    "changes": "profile.charm_wall_breakaway_long.es-structure.min-higher-high-distance=0.5; profile.charm_wall_breakaway_long.es-structure.min-higher-low-distance=1; profile.charm_wall_breakaway_long.long-regime-filter.max-distance-above-charm-wall=25",
    "delta_average_mae": 0.9822115384615273,
    "delta_net_profit": 72.5,
    "delta_score": 110.56238675213535,
    "delta_slow_12h_trades": 0.0,
    "delta_trades": 0.0,
    "delta_worst_mae": 125.35000000000002,
    "family": "strategy-profile",
    "from_run": "run_033",
    "label": "promote",
    "primary_metric": "score",
    "reason": "score delta 110.562 >= 0; net profit delta 72.5 >= -25; trade drop 0% <= 10%",
    "result": "accepted",
    "to_run": "run_036"
  },
  {
    "changes": "scalp-es-vwap-distance-min=20",
    "delta_average_mae": -2.2026639712488674,
    "delta_net_profit": 241.40000000000055,
    "delta_score": 238.58949015423786,
    "delta_slow_12h_trades": 0.0,
    "delta_trades": 1.0,
    "delta_worst_mae": 0.0,
    "family": "general",
    "from_run": "run_034",
    "label": "fallback-scalpesvwapdistancemin-20",
    "primary_metric": "score",
    "reason": "score delta 238.589 >= 0; net profit delta 241.4 >= -25; trade drop 0% <= 10%",
    "result": "accepted",
    "to_run": "run_037"
  },
  {
    "changes": "entry-veto-charm-pin-tail-risk-max-pullback-from-high=10; entry-veto-charm-pin-tail-risk-max-rolling-high-distance=15; entry-veto-charm-pin-tail-risk-max-vwap-acceleration=0.02; entry-veto-charm-pin-tail-risk-min-setup-quality-score=60",
    "delta_average_mae": -1.871226415094327,
    "delta_net_profit": 92.60000000000036,
    "delta_score": 89.78924648846987,
    "delta_slow_12h_trades": 0.0,
    "delta_trades": 0.0,
    "delta_worst_mae": 0.0,
    "family": "runtime-risk",
    "from_run": "run_035",
    "label": "charm-pin-tail-box-repair",
    "primary_metric": "worst_mae",
    "reason": "score delta 89.7892 >= 0; net profit delta 92.6 >= -25; trade drop 0% <= 10%; MAE delta 0 >= 0; slow trades delta 0 <= 0",
    "result": "accepted",
    "to_run": "run_038"
  },
  {
    "changes": "profile.charm_wall_breakaway_long.es-structure.min-higher-low-distance=1; profile.charm_wall_breakaway_long.es-vwap.max-distance=22; profile.charm_wall_breakaway_long.long-regime-filter.max-distance-above-charm-wall=25",
    "delta_average_mae": 0.35837912087912116,
    "delta_net_profit": -204.39999999999964,
    "delta_score": -203.3606590964573,
    "delta_slow_12h_trades": 0.0,
    "delta_trades": 1.0,
    "delta_worst_mae": 0.0,
    "family": "strategy-profile",
    "from_run": "run_036",
    "label": "promote",
    "primary_metric": "score",
    "reason": "score delta -203.361 < 0; net profit delta -204.4 < -25",
    "result": "mixed",
    "to_run": "run_039"
  },
  {
    "changes": "profile.charm_pin_pullback_long.long-regime-filter.dynamic-vwap-max-distance=25; profile.charm_pin_pullback_long.long-regime-filter.dynamic-vwap-volatility-multiplier=0.4; profile.charm_pin_pullback_long.long-regime-filter.recent-high-rejection-min-pullback=8",
    "delta_average_mae": 0.0,
    "delta_net_profit": 0.0,
    "delta_score": 0.0,
    "delta_slow_12h_trades": 0.0,
    "delta_trades": 0.0,
    "delta_worst_mae": 0.0,
    "family": "strategy-profile",
    "from_run": "run_037",
    "label": "charm-pin-local-extension-box",
    "primary_metric": "score",
    "reason": "score delta 0 >= 0; net profit delta 0 >= -25; trade drop 0% <= 10%",
    "result": "accepted",
    "to_run": "run_040"
  },
  {
    "changes": "profile.charm_wall_breakaway_long.es-vwap.max-distance=22; profile.charm_wall_breakaway_long.take-profit.max-distance=10; profile.charm_wall_breakaway_long.take-profit.multiplier=1",
    "delta_average_mae": 0.6543739279588294,
    "delta_net_profit": -146.70000000000073,
    "delta_score": -143.70145021917415,
    "delta_slow_12h_trades": 0.0,
    "delta_trades": 4.0,
    "delta_worst_mae": 0.0,
    "family": "take-profit",
    "from_run": "run_038",
    "label": "charm-wall-realization-trim",
    "primary_metric": "net_profit",
    "reason": "score delta -143.701 < 0; net profit delta -146.7 < -25",
    "result": "mixed",
    "to_run": "run_041"
  },
  {
    "changes": "ema-period=12",
    "delta_average_mae": -61.502182539682536,
    "delta_net_profit": -2607.1000000000004,
    "delta_score": -14219.200218408292,
    "delta_slow_12h_trades": 1.0,
    "delta_trades": -34.0,
    "delta_worst_mae": -3881.1,
    "family": "upstream-entry",
    "from_run": "run_039",
    "label": "fallback-emaperiod-12",
    "primary_metric": "score",
    "reason": "score delta -14219.2 < 0; net profit delta -2607.1 < -25; trade drop 32.0755% > 10%",
    "result": "rejected",
    "to_run": "run_042"
  },
  {
    "changes": "indicator-register-resolution=Second",
    "delta_average_mae": -108.95471698113207,
    "delta_net_profit": -3270.8,
    "delta_score": -15618.400284360587,
    "delta_slow_12h_trades": 2.0,
    "delta_trades": -28.0,
    "delta_worst_mae": -3874.2999999999997,
    "family": "upstream-entry",
    "from_run": "run_040",
    "label": "fallback-indicatorregisterresolution-Second",
    "primary_metric": "score",
    "reason": "score delta -15618.4 < 0; net profit delta -3270.8 < -25; trade drop 26.1682% > 10%",
    "result": "rejected",
    "to_run": "run_043"
  },
  {
    "changes": "entry-veto-extended-vwap-rejection-max-vwap-distance=27",
    "delta_average_mae": -4.5272281639928735,
    "delta_net_profit": 529.9000000000005,
    "delta_score": 460.89448830956644,
    "delta_slow_12h_trades": 0.0,
    "delta_trades": -8.0,
    "delta_worst_mae": -141.80000000000007,
    "family": "surgical-veto",
    "from_run": "run_041",
    "label": "extended-vwap-tail-boundary-nudge",
    "primary_metric": "worst_mae",
    "reason": "MAE delta -4.52723 < 0",
    "result": "mixed",
    "to_run": "run_044"
  },
  {
    "changes": "option-call-volume.min-increase-pct=0.05; option-strike-acceptance-seconds=45; profile.call_wall_acceptance_long.long-regime-filter.min-forward-dex-ratio-30m=0.03; profile.call_wall_acceptance_long.long-regime-filter.min-net-dex-volume=7.5e+08",
    "delta_average_mae": 58.587152777777774,
    "delta_net_profit": 2011.9000000000005,
    "delta_score": 13578.553448765433,
    "delta_slow_12h_trades": -1.0,
    "delta_trades": 25.0,
    "delta_worst_mae": 3755.75,
    "family": "option-strike-map",
    "from_run": "run_042",
    "label": "promote",
    "primary_metric": "score",
    "reason": "score delta 13578.6 >= 0; net profit delta 2011.9 >= -25; trade drop 0% <= 10%",
    "result": "accepted",
    "to_run": "run_045"
  },
  {
    "changes": "profile.charm_wall_breakaway_long.es-structure.min-higher-high-distance=1.5; profile.charm_wall_breakaway_long.es-structure.min-higher-low-distance=1; profile.charm_wall_breakaway_long.long-regime-filter.max-distance-above-charm-wall=25",
    "delta_average_mae": 107.89519230769228,
    "delta_net_profit": 3206.0999999999995,
    "delta_score": 15551.115300128204,
    "delta_slow_12h_trades": -2.0,
    "delta_trades": 26.0,
    "delta_worst_mae": 3874.2999999999997,
    "family": "strategy-profile",
    "from_run": "run_043",
    "label": "promote",
    "primary_metric": "score",
    "reason": "score delta 15551.1 >= 0; net profit delta 3206.1 >= -25; trade drop 0% <= 10%",
    "result": "accepted",
    "to_run": "run_046"
  },
  {
    "changes": "option-strike-acceptance-seconds=45; profile.call_wall_acceptance_long.dynamic-take-profit.max=5; profile.call_wall_acceptance_long.take-profit.distance=4.5",
    "delta_average_mae": -0.02254901960783684,
    "delta_net_profit": -15.400000000000546,
    "delta_score": -15.434340196077756,
    "delta_slow_12h_trades": 0.0,
    "delta_trades": 0.0,
    "delta_worst_mae": 0.0,
    "family": "take-profit",
    "from_run": "run_044",
    "label": "promote",
    "primary_metric": "net_profit",
    "reason": "score delta -15.4343 < 0",
    "result": "mixed",
    "to_run": "run_047"
  },
  {
    "changes": "option-call-volume.min-increase-pct=0.05; profile.call_wall_acceptance_long.long-regime-filter.min-forward-dex-ratio-30m=0.03; profile.call_wall_acceptance_long.long-regime-filter.min-net-dex-volume=5e+08",
    "delta_average_mae": -2.164073581560274,
    "delta_net_profit": 16.599999999999454,
    "delta_score": 12.355803516549713,
    "delta_slow_12h_trades": 0.0,
    "delta_trades": -2.0,
    "delta_worst_mae": 0.0,
    "family": "strategy-profile",
    "from_run": "run_045",
    "label": "call-wall-sustained-sample-builder",
    "primary_metric": "score",
    "reason": "score delta 12.3558 >= 0; net profit delta 16.6 >= -25; trade drop 2.06186% <= 10%",
    "result": "accepted",
    "to_run": "run_048"
  },
  {
    "changes": "adx-period=10",
    "delta_average_mae": -38.88628426171529,
    "delta_net_profit": -1107.8999999999996,
    "delta_score": -3101.6809364764667,
    "delta_slow_12h_trades": 1.0,
    "delta_trades": -17.0,
    "delta_worst_mae": -1523.6,
    "family": "upstream-entry",
    "from_run": "run_046",
    "label": "fallback-adxperiod-10",
    "primary_metric": "score",
    "reason": "score delta -3101.68 < 0; net profit delta -1107.9 < -25; trade drop 16.1905% > 10%",
    "result": "rejected",
    "to_run": "run_049"
  },
  {
    "changes": "profile.call_wall_acceptance_long.dynamic-take-profit.max=5; profile.call_wall_acceptance_long.long-regime-filter.min-forward-dex-ratio-30m=0.08",
    "delta_average_mae": 0.02254901960783684,
    "delta_net_profit": 15.400000000000546,
    "delta_score": 15.434340196077756,
    "delta_slow_12h_trades": 0.0,
    "delta_trades": 0.0,
    "delta_worst_mae": 0.0,
    "family": "take-profit",
    "from_run": "run_047",
    "label": "promote",
    "primary_metric": "net_profit",
    "reason": "score delta 15.4343 >= 0; net profit delta 15.4 >= -25; trade drop 0% <= 10%",
    "result": "accepted",
    "to_run": "run_050"
  },
  {
    "changes": "profile.charm_wall_breakaway_long.es-structure.min-higher-high-distance=1.5; profile.charm_wall_breakaway_long.es-structure.min-higher-low-distance=1; profile.charm_wall_breakaway_long.es-vwap.max-distance=22",
    "delta_average_mae": 2.430143565379055,
    "delta_net_profit": 1023.8000000000002,
    "delta_score": 1010.3155431258474,
    "delta_slow_12h_trades": 0.0,
    "delta_trades": 9.0,
    "delta_worst_mae": -16.450000000000045,
    "family": "strategy-profile",
    "from_run": "run_048",
    "label": "charm-wall-supported-extension-box",
    "primary_metric": "score",
    "reason": "score delta 1010.32 >= 0; net profit delta 1023.8 >= -25; trade drop 0% <= 10%",
    "result": "accepted",
    "to_run": "run_051"
  },
  {
    "changes": "profile.charm_wall_breakaway_long.es-structure.min-higher-high-distance=1.5; profile.charm_wall_breakaway_long.es-structure.min-higher-low-distance=1; profile.charm_wall_breakaway_long.take-profit.max-distance=6",
    "delta_average_mae": 36.51842840262111,
    "delta_net_profit": 1392.6000000000004,
    "delta_score": 3326.143708243382,
    "delta_slow_12h_trades": -1.0,
    "delta_trades": 20.0,
    "delta_worst_mae": 1381.8,
    "family": "take-profit",
    "from_run": "run_049",
    "label": "promote",
    "primary_metric": "net_profit",
    "reason": "score delta 3326.14 >= 0; net profit delta 1392.6 >= -25; trade drop 0% <= 10%",
    "result": "accepted",
    "to_run": "run_052"
  },
  {
    "changes": "option-call-volume.min-increase-pct=0.15; profile.call_wall_acceptance_long.long-regime-filter.min-forward-dex-ratio-30m=0.08; profile.call_wall_acceptance_long.long-regime-filter.min-net-dex-volume=1.5e+09",
    "delta_average_mae": -1.9073946599916525,
    "delta_net_profit": -1230.9000000000005,
    "delta_score": -1216.129647545542,
    "delta_slow_12h_trades": 0.0,
    "delta_trades": -8.0,
    "delta_worst_mae": 16.450000000000045,
    "family": "strategy-profile",
    "from_run": "run_050",
    "label": "promote",
    "primary_metric": "score",
    "reason": "score delta -1216.13 < 0; net profit delta -1230.9 < -25",
    "result": "mixed",
    "to_run": "run_053"
  },
  {
    "changes": "profile.breakout_long_no_0dte.dynamic-take-profit.max=4; profile.breakout_long_no_0dte.es-vwap.slope-min=0.1; profile.breakout_long_no_0dte.take-profit.distance=4",
    "delta_average_mae": 1.3850942318674981,
    "delta_net_profit": 120.90000000000055,
    "delta_score": 122.4797830144671,
    "delta_slow_12h_trades": 0.0,
    "delta_trades": -1.0,
    "delta_worst_mae": 0.0,
    "family": "take-profit",
    "from_run": "run_051",
    "label": "no-0dte-breakout-realization-tighten",
    "primary_metric": "net_profit",
    "reason": "score delta 122.48 >= 0; net profit delta 120.9 >= -25; trade drop 0.961538% <= 10%",
    "result": "accepted",
    "to_run": "run_054"
  },
  {
    "changes": "profile.call_wall_acceptance_long.dynamic-take-profit.max=5",
    "delta_average_mae": -0.44547370350008464,
    "delta_net_profit": 163.19999999999982,
    "delta_score": 160.0152505558599,
    "delta_slow_12h_trades": 0.0,
    "delta_trades": -5.0,
    "delta_worst_mae": 0.0,
    "family": "take-profit",
    "from_run": "run_052",
    "label": "call-wall-realization-persistence-box",
    "primary_metric": "net_profit",
    "reason": "score delta 160.015 >= 0; net profit delta 163.2 >= -25; trade drop 4.62963% <= 10%",
    "result": "accepted",
    "to_run": "run_055"
  },
  {
    "changes": "entry-veto-extended-vwap-rejection-max-higher-high-distance=7.5; entry-veto-extended-vwap-rejection-max-rsi-slope=4.4; entry-veto-extended-vwap-rejection-min-pullback-from-high=0",
    "delta_average_mae": 4.306345868381982,
    "delta_net_profit": -97.69999999999982,
    "delta_score": -116.2608839752047,
    "delta_slow_12h_trades": 0.0,
    "delta_trades": -7.0,
    "delta_worst_mae": -16.450000000000045,
    "family": "surgical-veto",
    "from_run": "run_053",
    "label": "extended-vwap-near-miss-tail-repair",
    "primary_metric": "worst_mae",
    "reason": "score delta -116.261 < 0; net profit delta -97.7 < -25",
    "result": "mixed",
    "to_run": "run_056"
  },
  {
    "changes": "option-strike-acceptance-seconds=30; profile.call_wall_acceptance_long.dynamic-take-profit.max=5; profile.call_wall_acceptance_long.long-regime-filter.min-forward-dex-ratio-30m=0.08",
    "delta_average_mae": -2.11127450980392,
    "delta_net_profit": 35.79999999999927,
    "delta_score": 32.628174346404194,
    "delta_slow_12h_trades": 0.0,
    "delta_trades": 0.0,
    "delta_worst_mae": 0.0,
    "family": "take-profit",
    "from_run": "run_054",
    "label": "call-wall-persistence-containment",
    "primary_metric": "net_profit",
    "reason": "score delta 32.6282 >= 0; net profit delta 35.8 >= -25; trade drop 0% <= 10%",
    "result": "accepted",
    "to_run": "run_057"
  },
  {
    "changes": "__router.valid-0dte-profiles=breakout_long,pullback_long,squeeze_long,wall_reclaim_long,wall_breakout_retest_long,late_day_pin_fade,negative_gamma_momentum_long,trend_day_pullback_long,charm_pin_pullback_long,charm_wall_breakaway_long,call_wall_acceptance_long,delta_charm_breakout_long; profile.delta_charm_breakout_long.enabled=true",
    "delta_average_mae": 0.9631372549019659,
    "delta_net_profit": -113.0,
    "delta_score": -112.54434689542359,
    "delta_slow_12h_trades": 0.0,
    "delta_trades": -2.0,
    "delta_worst_mae": 0.0,
    "family": "strategy-profile",
    "from_run": "run_055",
    "label": "delta-charm-breakout-attribution-probe",
    "primary_metric": "score",
    "reason": "score delta -112.544 < 0; net profit delta -113 < -25",
    "result": "mixed",
    "to_run": "run_058"
  },
  {
    "changes": "higher-timeframe-resolution=30min",
    "delta_average_mae": -2.3989512083903293,
    "delta_net_profit": 1328.6000000000004,
    "delta_score": 1332.3905315207467,
    "delta_slow_12h_trades": 0.0,
    "delta_trades": 15.0,
    "delta_worst_mae": 0.0,
    "family": "upstream-entry",
    "from_run": "run_056",
    "label": "fallback-highertimeframeresolution-30min",
    "primary_metric": "score",
    "reason": "score delta 1332.39 >= 0; net profit delta 1328.6 >= -25; trade drop 0% <= 10%",
    "result": "accepted",
    "to_run": "run_059"
  },
  {
    "changes": "drift-trade-quantity-multiplier=0.5",
    "delta_average_mae": 0.20343137254901933,
    "delta_net_profit": 50.400000000000546,
    "delta_score": 50.70614705882326,
    "delta_slow_12h_trades": 0.0,
    "delta_trades": 0.0,
    "delta_worst_mae": 0.0,
    "family": "general",
    "from_run": "run_057",
    "label": "fallback-drifttradequantitymultiplier-0.5",
    "primary_metric": "score",
    "reason": "score delta 50.7061 >= 0; net profit delta 50.4 >= -25; trade drop 0% <= 10%",
    "result": "accepted",
    "to_run": "run_060"
  }
]
